commitcrafter/__init__.py
commitcrafter/cli.py
commitcrafter/commit_generator.py
commitcrafter/commitcrafter.py
commitcrafter/exceptions.py
commitcrafter/models.py
commitcrafter/prompt.txt
commitcrafter-0.3.2.dist-info/METADATA
commitcrafter-0.3.2.dist-info/WHEEL
commitcrafter-0.3.2.dist-info/entry_points.txt
commitcrafter-0.3.2.dist-info/RECORD
