Metadata-Version: 2.3
Name: commitcrafter
Version: 0.3.2
Summary: A CLI tool to generate commit messages based on git diffs using AI
Author: mpruvot
Author-email: marius.pruvot@outlook.fr
Requires-Python: >=3.12,<4.0
Classifier: Programming Language :: Python :: 3
Classifier: Programming Language :: Python :: 3.12
Classifier: Programming Language :: Python :: 3.13
Requires-Dist: gitpython (>=3.1.43,<4.0.0)
Requires-Dist: mypy (>=1.14.1,<2.0.0)
Requires-Dist: openai (>=1.23.1,<2.0.0)
Requires-Dist: pre-commit (>=4.0.1,<5.0.0)
Requires-Dist: pydantic-ai (>=0.0.19,<0.0.20)
Requires-Dist: pyperclip (>=1.9.0,<2.0.0)
Requires-Dist: pytest (>=8.1.1,<9.0.0)
Requires-Dist: rich (>=13.7.1,<14.0.0)
Requires-Dist: ruff (>=0.9.2,<0.10.0)
Requires-Dist: typer (==0.12.3)
